{
  "entrypoint": "index_yp.html",
  "shell": "src/yp-app.html",
  "fragments": [
    "src/yp-domain/yp-domain.html",
    "src/yp-community/yp-community.html",
    "src/yp-group/yp-group.html",
    "src/yp-post/yp-post.html",
    "src/yp-dialog-container/yp-dialog-container-logged-in.html",
    "src/yp-dialog-container/yp-dialog-container-admin.html"
  ],
  "sourceGlobs": [
    "src/**/*",
    "images/**/*",
    "bower.json"
  ],
  "includeDependencies": [
    "manifest.json",
    "bower_components/webcomponentsjs/webcomponents-lite.min.js"
  ]
}
